{
  "configVersion": 2,
  "ctcpTimeLocale": ["en-US", "UTC"],
  "serverArray": [
    {
      "disabled": false,
      "name": "DALnet",
      "host": "lion.dal.net",
      "port": 6697,
      "tls": true,
      "verify": true,
      "proxy": false,
      "reconnect": false,
      "logging": false,
      "password": "",
      "saslUsername": "",
      "saslPassword": "",
      "identifyNick": "",
      "identifyCommand": "",
      "nick": "MyNickname",
      "altNick": "",
      "recoverNick": false,
      "user": "user",
      "real": "John Doe",
      "modes": "+i",
      "channelList": ["#myChannel", "#otherChannel"]
    }
  ]
}
