{
  "configVersion": 2,
  "loginUsers": [
    {
      "userid": 1,
      "user": "user1",
      "name": "user1",
      "hash": "xxxxxxxxxxxxxxxxxxxxxxxxxxxxxxxxxxxxxxxxxx"
    }
  ],
  "securityContact": "mailto:security@example.com",
  "securityExpires": "Fri, 1 Apr 2022 08:00:00 -0600",

  "serverTlsKey": "/home/user1/tls/privkey.pem",
  "serverTlsCert": "/home/user1/tls/fullchain.pem",
  "tls": true,
  "port": 3003,
  "pidFilename": "/home/user1/tmp/ircHybridClient.PID",
  "instanceNumber": 0,
  "logRotationInterval": "7d",
  "logRotationSize": "1M",
  "accessLogOnlyErrors": false,

  "sessionRollingCookie": false,
  "sessionExpireAfterSec": 86400,
  "cookieSecret": "xxxxxxxxxxxxxxxx",
  "sessionEnableRedis": false,
  "sessionRedisPrefix": "irc001:",
  "sessionRedisPassword": "",

  "enableRemoteLogin": false,
  "remoteAuthHost": "http://127.0.0.1:3500",
  "remoteCallbackHost": "http://localhost:3003",
  "remoteClientId": "irc_client_1",
  "remoteClientSecret": "xxxxxxxx",
  "remoteScope": "irc.all",

  "disableServerListEditor": false,
  "persistIrcMessageCache": false,
  "ircSocketLocalAddress": "",
  "serveHtmlHelpDocs": false,
  "customBeepSounds": false,

  "enableSocks5Proxy": false,
  "socks5Host": "127.0.0.1",
  "socks5Port": 12345,
  "socks5Username": null,
  "socks5Password": null
}
